<?xml version="1.0"?>
<Checkpoint Version="22" Minor="0">
	<BUILD_NUMBER Name="5076996"/>
	<FULL_BUILD Name="SW Build 5076996 on Wed May 22 18:37:14 MDT 2024"/>
	<PRODUCT Name="Vivado v2024.1 (64-bit)"/>
	<Part Name="xc7a100tcsg324-1"/>
	<FeatureSet Name="FeatureSet_Classic"/>
	<NEXTGEN_VERSAL Name="0"/>
	<Top Name="gameTop"/>
	<DisableAutoIOBuffers Name="0"/>
	<OutOfContext Name="0"/>
	<MacroLevel Name="1"/>
	<RunGenerated Name="1"/>
	<HDPlatform Name="0"/>
	<XPMLIBRARY Name="XPM_CDC"/>
	<XPMLIBRARY Name="XPM_MEMORY"/>
	<File Type="VERILOG_STUB" Name="gameTop_stub.v" ModTime="1776556906"/>
	<File Type="VHDL_STUB" Name="gameTop_stub.vhdl" ModTime="1776556906"/>
	<File Type="PARAMXML" Name="gameTop_param.xml" ModTime="1776556906"/>
	<File Type="PARAMXML" Name="gameTop_param.xml" ModTime="1776556906"/>
	<File Type="SHAPE" Name="gameTop.shape" ModTime="1776556906"/>
	<File Type="XN" Name="gameTop.xn" ModTime="1776556906"/>
	<File Type="EDIF" Name="gameTop.edf" ModTime="1776556906"/>
	<File Type="INCR" Name="gameTop.incr" ModTime="1776556906"/>
	<File Type="RDA" Name="gameTop.rda" ModTime="1776556906"/>
	<File Type="JSON_RDA" Name="gameTop_rda.json" ModTime="1776556906"/>
	<File Type="WDF" Name="gameTop.wdf" ModTime="1776556906"/>
	<File Type="SYNTH" Name="gameTop.synth" ModTime="1776556906"/>
</Checkpoint>

